visula-0.1.0.dist-info/METADATA
visula-0.1.0.dist-info/WHEEL
visula/__init__.py
visula/application.py
visula/figure.py
visula/expression.py
visula/instance_buffer.py
visula/math.py
visula/uniform.py
visula/_visula_pyo3.cpython-38-powerpc64le-linux-gnu.so
visula-0.1.0.dist-info/RECORD
